sphinxcontrib/qthelp/__init__.py
sphinxcontrib/qthelp/locales/sphinxcontrib.qthelp.pot
sphinxcontrib/qthelp/locales/.tx/config
sphinxcontrib/qthelp/locales/ar/LC_MESSAGES/sphinxcontrib.qthelp.mo
sphinxcontrib/qthelp/locales/ar/LC_MESSAGES/sphinxcontrib.qthelp.po
sphinxcontrib/qthelp/locales/bn/LC_MESSAGES/sphinxcontrib.qthelp.mo
sphinxcontrib/qthelp/locales/bn/LC_MESSAGES/sphinxcontrib.qthelp.po
sphinxcontrib/qthelp/locales/ca/LC_MESSAGES/sphinxcontrib.qthelp.mo
sphinxcontrib/qthelp/locales/ca/LC_MESSAGES/sphinxcontrib.qthelp.po
sphinxcontrib/qthelp/locales/cs/LC_MESSAGES/sphinxcontrib.qthelp.mo
sphinxcontrib/qthelp/locales/cs/LC_MESSAGES/sphinxcontrib.qthelp.po
sphinxcontrib/qthelp/locales/cy/LC_MESSAGES/sphinxcontrib.qthelp.mo
sphinxcontrib/qthelp/locales/cy/LC_MESSAGES/sphinxcontrib.qthelp.po
sphinxcontrib/qthelp/locales/da/LC_MESSAGES/sphinxcontrib.qthelp.mo
sphinxcontrib/qthelp/locales/da/LC_MESSAGES/sphinxcontrib.qthelp.po
sphinxcontrib/qthelp/locales/de/LC_MESSAGES/sphinxcontrib.qthelp.mo
sphinxcontrib/qthelp/locales/de/LC_MESSAGES/sphinxcontrib.qthelp.po
sphinxcontrib/qthelp/locales/el/LC_MESSAGES/sphinxcontrib.qthelp.mo
sphinxcontrib/qthelp/locales/el/LC_MESSAGES/sphinxcontrib.qthelp.po
sphinxcontrib/qthelp/locales/eo/LC_MESSAGES/sphinxcontrib.qthelp.mo
sphinxcontrib/qthelp/locales/eo/LC_MESSAGES/sphinxcontrib.qthelp.po
sphinxcontrib/qthelp/locales/es/LC_MESSAGES/sphinxcontrib.qthelp.mo
sphinxcontrib/qthelp/locales/es/LC_MESSAGES/sphinxcontrib.qthelp.po
sphinxcontrib/qthelp/locales/et/LC_MESSAGES/sphinxcontrib.qthelp.mo
sphinxcontrib/qthelp/locales/et/LC_MESSAGES/sphinxcontrib.qthelp.po
sphinxcontrib/qthelp/locales/eu/LC_MESSAGES/sphinxcontrib.qthelp.mo
sphinxcontrib/qthelp/locales/eu/LC_MESSAGES/sphinxcontrib.qthelp.po
sphinxcontrib/qthelp/locales/fa/LC_MESSAGES/sphinxcontrib.qthelp.mo
sphinxcontrib/qthelp/locales/fa/LC_MESSAGES/sphinxcontrib.qthelp.po
sphinxcontrib/qthelp/locales/fi/LC_MESSAGES/sphinxcontrib.qthelp.mo
sphinxcontrib_qthelp-1.0.4.dist-info/LICENSE
sphinxcontrib_qthelp-1.0.4.dist-info/WHEEL
sphinxcontrib_qthelp-1.0.4.dist-info/METADATA
sphinxcontrib_qthelp-1.0.4.dist-info/RECORD
